<objects attr-sync="on">
  <object type="LongoMatch.Gui.CapturerBin" palette-category="General" allow-children="false" base-type="Gtk.Bin">
    <itemgroups>
      <itemgroup label="CapturerBin Properties">
        <property name="Capturing" />
      </itemgroup>
    </itemgroups>
    <signals />
  </object>
  <object type="LongoMatch.Gui.PlayerBin" palette-category="General" allow-children="false" base-type="Gtk.Bin">
    <itemgroups>
      <itemgroup label="IPlayerBin Properties">
        <property name="Sensitive" />
      </itemgroup>
    </itemgroups>
    <signals>
      <itemgroup label="PlayerBin Signals">
        <signal name="Tick" />
        <signal name="PlayStateChanged" />
      </itemgroup>
    </signals>
  </object>
  <object type="LongoMatch.Gui.PlayerCapturerBin" palette-category="General" allow-children="false" base-type="Gtk.Bin">
    <itemgroups>
      <itemgroup label="IPlayerBin Properties">
        <property name="Sensitive" />
      </itemgroup>
    </itemgroups>
    <signals>
      <itemgroup label="IPlayerBin Signals">
        <signal name="PlayStateChanged" />
      </itemgroup>
    </signals>
  </object>
  <object type="LongoMatch.Gui.VideoWindow" palette-category="General" allow-children="false" base-type="Gtk.Bin">
    <itemgroups>
      <itemgroup label="VideoWindow Properties">
        <property name="Ready" />
      </itemgroup>
    </itemgroups>
    <signals>
      <itemgroup label="VideoWindow Signals">
        <signal name="ReadyEvent" />
        <signal name="ExposeEvent" />
        <signal name="ButtonPressEvent" />
        <signal name="ScrollEvent" />
      </itemgroup>
    </signals>
  </object>
</objects>